sksurgerytrackervisualisation/__init__.py
sksurgerytrackervisualisation/__main__.py
sksurgerytrackervisualisation/_version.py
sksurgerytrackervisualisation/algorithms/__init__.py
sksurgerytrackervisualisation/algorithms/algorithms.py
sksurgerytrackervisualisation/algorithms/background_image.py
sksurgerytrackervisualisation/algorithms/icp.py
sksurgerytrackervisualisation/overlay_app/__init__.py
sksurgerytrackervisualisation/overlay_app/overlay.py
sksurgerytrackervisualisation/shapes/__init__.py
sksurgerytrackervisualisation/shapes/cone.py
sksurgerytrackervisualisation/shapes/dynamic_point_cloud.py
sksurgerytrackervisualisation/shapes/sphere.py
sksurgerytrackervisualisation/ui/__init__.py
sksurgerytrackervisualisation/ui/sksurgerytrackervisualisation_cl.py
sksurgerytrackervisualisation/ui/sksurgerytrackervisualisation_demo.py
scikit_surgerytrackervisualisation-0.0.5.dist-info/LICENSE
scikit_surgerytrackervisualisation-0.0.5.dist-info/METADATA
scikit_surgerytrackervisualisation-0.0.5.dist-info/WHEEL
scikit_surgerytrackervisualisation-0.0.5.dist-info/entry_points.txt
scikit_surgerytrackervisualisation-0.0.5.dist-info/top_level.txt
scikit_surgerytrackervisualisation-0.0.5.dist-info/RECORD
