Metadata-Version: 2.1
Name: scikit-surgerytrackervisualisation
Version: 0.0.5
Summary: Provides a live visualisation of tracking data from a scikit-surgerytracker source
Home-page: https://github.com/SciKit-Surgery/scikit-surgerytrackervisualisation
Author: Stephen Thompson
Author-email: s.thompson@ucl.ac.uk
License: BSD-3 license
Keywords: medical imaging
Platform: UNKNOWN
Classifier: Development Status :: 3 - Alpha
Classifier: Intended Audience :: Developers
Classifier: Intended Audience :: Healthcare Industry
Classifier: Intended Audience :: Information Technology
Classifier: Intended Audience :: Science/Research
Classifier: License :: OSI Approved :: BSD License
Classifier: Programming Language :: Python
Classifier: Programming Language :: Python :: 2
Classifier: Programming Language :: Python :: 3
Classifier: Topic :: Scientific/Engineering :: Information Analysis
Classifier: Topic :: Scientific/Engineering :: Medical Science Apps.
Requires-Dist: numpy
Requires-Dist: vtk
Requires-Dist: PySide2
Requires-Dist: scikit-surgeryvtk (>=0.9.0)
Requires-Dist: scikit-surgeryimage (>=0.6.0)
Requires-Dist: scikit-surgerycore
Requires-Dist: scikit-surgeryutils
Requires-Dist: scikit-surgerynditracker
Requires-Dist: scikit-surgeryarucotracker
